vshelpers/__init__.py
vshelpers/evaluations/__init__.py
vshelpers/evaluations/overlap.py
vshelpers/evaluations/sample.py
vshelpers/helpers/__init__.py
vshelpers/helpers/clean.py
vshelpers/helpers/curation.py
vshelpers/helpers/general.py
vshelpers/helpers/provider.py
vshelpers/helpers/statistic.py
vshelpers-0.0.6.dist-info/METADATA
vshelpers-0.0.6.dist-info/WHEEL
vshelpers-0.0.6.dist-info/top_level.txt
vshelpers-0.0.6.dist-info/RECORD
