Metadata-Version: 2.1
Name: vshelpers
Version: 0.0.6
Summary: Helper functions for veraset clusters
Author: Nicholas Dela Fuente
Author-email: nick.delafuente1@gmail.com
Classifier: Programming Language :: Python :: 3
Classifier: License :: OSI Approved :: MIT License
Classifier: Operating System :: OS Independent
Requires-Python: >=3.6
